{
  "2": {
    "default": [
      {
        "col": 2
      }
    ],
    "col": [
      {
        "row": 1
      },
      {
        "row": 1
      }
    ],
    "row" : [
      {
        "col": 1
      },
      {
        "col": 1
      }
    ]
  },
  "3": {
    "default": [
      {
        "col": 3
      }
    ],
    "col": [
      {
        "row": 1
      },
      {
        "row": 2
      }
    ],
    "row": [
      {
        "col": 1
      },
      {
        "col": 2
      }
    ]
  },
  "4": {
     "default": [
      {
        "col": 2
      },
       {
        "col": 2
      }
    ],
    "col": [
      {
        "row": 1
      },
      {
        "row": 3
      }
    ],
    "row": [
      {
        "col": 1
      },
      {
        "col": 3
      }
    ]
  },
  "5": {
    "default": [
      {
        "col": 2
      },
       {
        "col": 3
      }
    ],
    "col": [
      {
        "row": 2
      },
      {
        "row": 3
      }
    ],
    "row": [
      {
        "col": 2
      },
      {
        "col": 3
      }
    ]
  }
}

